README.md
setup.py
gym_connect4/__init__.py
gym_connect4.egg-info/PKG-INFO
gym_connect4.egg-info/SOURCES.txt
gym_connect4.egg-info/dependency_links.txt
gym_connect4.egg-info/requires.txt
gym_connect4.egg-info/top_level.txt
gym_connect4/envs/__init__.py
gym_connect4/envs/connect4_env.py