Metadata-Version: 1.0
Name: gym-connect4
Version: 0.1
Summary: OpenAI gym environment for Connect 4
Home-page: https://github.com/Danielhp95/gym-connect4
Author: Sarios
Author-email: madness@xcape.com
License: UNKNOWN
Platform: UNKNOWN
